moxy/__init__.py
moxy/main.py
moxy/py.typed
moxy/version.py
moxy-0.1.0.dist-info/LICENSE
moxy-0.1.0.dist-info/METADATA
moxy-0.1.0.dist-info/WHEEL
moxy-0.1.0.dist-info/top_level.txt
moxy-0.1.0.dist-info/RECORD
